{
	"$schema": "vscode://schemas/color-theme",
	"name": "Dark Default Colors",
	"colors": {
		// global colors, used if not overridden by controls themselves
		"focusBorder":"#362822",
		"foreground":"#A76046",
		
		"errorForeground": "#D0FF00",
		"selection.background": "#3A2B25",
		//"contrastBorder": "", // useless borders
		//"contrastActiveBorder": "", // useless borders around focused element
		//"textSeparator.foreground": "", // no idea
		

		"titleBar.activeBackground": "#291F1B",
		"titleBar.inactiveBackground": "#130E0C",
		"titleBar.border": "#000000",
		"titleBar.activeForeground": "#08723F",
		"titleBar.inactiveForeground": "#08723F",
		//"editorGroupHeader.tabsBorder": "#00FF00",
		"editorGroupHeader.tabsBackground": "#1A1412",
		"editorGroupHeader.noTabsBackground": "#1A1412",
		"editorGroup.background": "#251C19",
		"editorGroup.border": "#1F1815",
		"editorGroup.dropBackground": "#000000",
		
		// tabs seem part of editor groups
		"tab.activeBackground": "#291F1B",
		"tab.activeForeground": "#A76046",
		"tab.inactiveBackground": "#1A1412",
		"tab.inactiveForeground": "#A76046",
		"tab.border": "#000000",

		"activityBar.background": "#251C19",
		"activityBarBadge.background": "#08723F",
		"activityBarBadge.foreground": "#01EB76",
		"activityBar.border": "#1F1815",
		"activityBar.foreground": "#413029",
		"activityBar.dropBackground": "#000000",
		
		"sideBar.background": "#251C19",
		"sideBar.foreground": "#A76046",		
		"sideBarTitle.foreground": "#A76046",
		"sideBarSectionHeader.background": "#251C19",

		// small badges
		"badge.background": "#08723F",
		"badge.foreground": "#01EB76",

		// file list
		"list.activeSelectionBackground": "#3F2011",
		"list.activeSelectionForeground": "#A76046",
		"list.inactiveSelectionBackground": "#3F2011",
		"list.inactiveSelectionForeground": "#A76046",
		"list.focusBackground": "#5C2C16",
		"list.focusForeground": "#A76046",
		"list.inactiveFocusBackground": "#5C2C16",
		"list.inactiveFocusForeground": "#A76046",
		"list.hoverBackground": "#522715",
		"list.hoverForeground": "#A76046",
		"list.highlightForeground": "#A76046",
		"list.dropBackground": "#000000",
		
		// debug notifications etc
		"notification.background": "#054D2A",
		"notification.foreground": "#01EB76",
		"notification.buttonBackground": "#08723F",
		"notification.buttonForeground": "#01EB76",
		"notification.buttonHoverBackground": "#086638",
		//"notification.errorBackground": "",
		//"notification.errorForeground": "",
		//"notification.infoBackground": "",
		//"notification.infoForeground": "",
		//"notification.warningBackground": "",
		//"notification.warningForeground": "",
		// bright magenta: #C40072
		// text editor
		"editor.background": "#291F1B",
		"editor.foreground": "#A76046",
		"editor.selectionBackground": "#163248",
		"editor.inactiveSelectionBackground": "#33231D",
		"editor.selectionHighlightBackground": "#3A2B25",
		"editor.hoverHighlightBackground": "#16324866",
		"editorRuler.foreground": "#241B18",
		"editorLineNumber.foreground": "#540D84",
		"editorCursor.background": "#2AA3FF",
		"editorCursor.foreground": "#0048B5",
		"editor.lineHighlightBorder": "#221A17",
		"editor.lineHighlightBackground": "#221A17",
		
		"editorIndentGuide.background": "#241B18",
		"editorWhitespace.foreground": "#241B18",
		
		"editorWarning.foreground": "#D0FF00",
		"editorWarning.border": "#D0FF0000",
		"editorError.foreground": "#FF4524",
		"editorError.border": "#FF452400",

		"editorBracketMatch.background": "#13376E",
		"editorBracketMatch.border": "#13376E",
		
		"editorSuggestWidget.foreground": "#017B99",
		"editorSuggestWidget.background": "#20192B",
		"editorSuggestWidget.border": "#20192B88",
		"editorSuggestWidget.highlightForeground": "#00A3D0",
		"editorSuggestWidget.selectedBackground": "#017B9922",

		// find (hover widget), tooltip (widget)
		"editorWidget.background": "#1F1815",
		"editorWidget.border": "#1F181588",
		"editorHoverWidget.background": "#1F1815",
		"editorHoverWidget.border": "#1F181588",

		"widget.shadow": "#1F1815",
		

		// ctrl-p popup
		"input.background": "#270F36",
		"input.foreground": "#00A3D0",
		"input.border": "#270F36",
		"input.placeholderForeground": "#4F2A68",
		"inputOption.activeBorder": "#00FF00",

		// console section
		"dropdown.background": "#291F1B",
		"dropdown.foreground": "#A76046",
		"dropdown.border": "#251C19",
		"panel.background": "#251C19",
		"panel.border": "#251C19",
		"panelTitle.activeBorder": "#251C19",
		"panelTitle.activeForeground": "#A76046",
		"panelTitle.inactiveForeground": "#6A3E2E",
		"terminal.foreground": "#A76046",
		"terminal.background": "#1F1815",

		// status bar
		"statusBar.background": "#251C19",
		"statusBar.foreground": "#9F3000",
		"statusBarItem.hoverBackground": "#000000",

		// scroll bar
		"scrollbar.shadow": "#1F1815",
		"scrollbarSlider.activeBackground": "#3B005FAA",
		"scrollbarSlider.background": "#3B005F66",
		"scrollbarSlider.hoverBackground": "#3B005FAA",
		
		"editorOverviewRuler.findMatchForeground": "#3A2B25",
		"editorOverviewRuler.border": "#291F1B",
		"editorOverviewRuler.commonContentForeground": "",
		"editorOverviewRuler.currentContentForeground": "",
		"editorOverviewRuler.addedForeground": "",
		"editorOverviewRuler.modifiedForeground": "",
		"editorOverviewRuler.deletedForeground": "",
		"editorOverviewRuler.errorForeground": "",
		"editorOverviewRuler.warningForeground": "",
		"editorOverviewRuler.incomingContentForeground": "",
		"editorOverviewRuler.infoForeground": "",
		"editorOverviewRuler.rangeHighlightForeground": "#ffff00",
		"editorOverviewRuler.selectionHighlightForeground": "#3A2B25",
		"editorOverviewRuler.wordHighlightForeground": "#00ff00",
		"editorOverviewRuler.wordHighlightStrongForeground": "#ff00ff",

		// diff
		"diffEditor.removedTextBackground": "#50242488",
		"diffEditor.removedTextBorder": "#50242488",
		"diffEditor.insertedTextBackground": "#1A3A2288",
		"diffEditor.insertedTextBorder": "#1A3A2288"

	}
}